magnus_extension_catalog_s3/integration.py
magnus_extension_catalog_s3/s3.py
magnus_extension_catalog_s3-0.2.0.dist-info/WHEEL
magnus_extension_catalog_s3-0.2.0.dist-info/entry_points.txt
magnus_extension_catalog_s3-0.2.0.dist-info/METADATA
magnus_extension_catalog_s3-0.2.0.dist-info/RECORD
